trade_metrics/__init__.py
trade_metrics/metrics.py
trade_metrics/visualize_perf.py
trade_metrics-0.0.5.dist-info/LICENSE
trade_metrics-0.0.5.dist-info/METADATA
trade_metrics-0.0.5.dist-info/WHEEL
trade_metrics-0.0.5.dist-info/top_level.txt
trade_metrics-0.0.5.dist-info/RECORD
